tickit/__init__.py
tickit/__main__.py
tickit/_version.py
tickit/cli.py
tickit/adapters/__init__.py
tickit/adapters/epics.py
tickit/adapters/http.py
tickit/adapters/system.py
tickit/adapters/tcp.py
tickit/adapters/utils.py
tickit/adapters/zmq.py
tickit/adapters/io/__init__.py
tickit/adapters/io/epics_io.py
tickit/adapters/io/http_io.py
tickit/adapters/io/tcp_io.py
tickit/adapters/io/zeromq_push_io.py
tickit/adapters/specifications/__init__.py
tickit/adapters/specifications/http_endpoint.py
tickit/adapters/specifications/regex_command.py
tickit/core/__init__.py
tickit/core/adapter.py
tickit/core/device.py
tickit/core/simulation.py
tickit/core/typedefs.py
tickit/core/components/__init__.py
tickit/core/components/component.py
tickit/core/components/device_component.py
tickit/core/components/system_component.py
tickit/core/management/__init__.py
tickit/core/management/event_router.py
tickit/core/management/ticker.py
tickit/core/management/schedulers/__init__.py
tickit/core/management/schedulers/base.py
tickit/core/management/schedulers/master.py
tickit/core/management/schedulers/nested.py
tickit/core/state_interfaces/__init__.py
tickit/core/state_interfaces/internal.py
tickit/core/state_interfaces/kafka.py
tickit/core/state_interfaces/state_interface.py
tickit/devices/__init__.py
tickit/devices/iobox.py
tickit/devices/sink.py
tickit/devices/source.py
tickit/utils/__init__.py
tickit/utils/byte_format.py
tickit/utils/singleton.py
tickit/utils/topic_naming.py
tickit/utils/configuration/__init__.py
tickit/utils/configuration/loading.py
tickit/utils/configuration/tagged_union.py
tickit-0.4.3.dist-info/LICENSE
tickit-0.4.3.dist-info/METADATA
tickit-0.4.3.dist-info/WHEEL
tickit-0.4.3.dist-info/entry_points.txt
tickit-0.4.3.dist-info/top_level.txt
tickit-0.4.3.dist-info/RECORD
