Metadata-Version: 2.1
Name: tickit
Version: 0.4.3
Summary: Event-based device simulation framework
Author-email: Callum Forrester <callum.forrester@diamond.ac.uk>
License: Apache License
Project-URL: GitHub, https://github.com/dls-controls/tickit
Classifier: Development Status :: 4 - Beta
Classifier: License :: OSI Approved :: Apache Software License
Classifier: Programming Language :: Python :: 3.9
Classifier: Programming Language :: Python :: 3.10
Requires-Python: >=3.9
License-File: LICENSE
Requires-Dist: aiohttp
Requires-Dist: aiokafka
Requires-Dist: aiozmq
Requires-Dist: immutables
Requires-Dist: pydantic >=2.0
Requires-Dist: pyyaml
Requires-Dist: pyzmq
Requires-Dist: softioc
Requires-Dist: typing-extensions
Requires-Dist: click !=8.1.4,!=8.1.5
Provides-Extra: dev
Requires-Dist: black ; extra == 'dev'
Requires-Dist: pyright ; extra == 'dev'
Requires-Dist: flake8-isort ; extra == 'dev'
Requires-Dist: Flake8-pyproject ; extra == 'dev'
Requires-Dist: pipdeptree ; extra == 'dev'
Requires-Dist: pre-commit ; extra == 'dev'
Requires-Dist: pydata-sphinx-theme >=0.12 ; extra == 'dev'
Requires-Dist: pytest-cov ; extra == 'dev'
Requires-Dist: pytest-flake8 ; extra == 'dev'
Requires-Dist: pytest-black ; extra == 'dev'
Requires-Dist: pytest-asyncio ; extra == 'dev'
Requires-Dist: pytest-pydocstyle ; extra == 'dev'
Requires-Dist: sphinx <=7.2.6 ; extra == 'dev'
Requires-Dist: sphinx-autobuild ; extra == 'dev'
Requires-Dist: sphinx-copybutton ; extra == 'dev'
Requires-Dist: sphinx-design ; extra == 'dev'
Requires-Dist: tox-direct ; extra == 'dev'
Requires-Dist: mock ; extra == 'dev'
Requires-Dist: types-mock ; extra == 'dev'
Requires-Dist: types-PyYAML ; extra == 'dev'
Requires-Dist: aioca ; extra == 'dev'
